hdl/4_23_fulladder/hdl/sv/fulladder.sv
module fulladder (
	input   logic a, b, cin,
	output  logic s, cout
);

	logic p, g;

  always_comb // equivalent to always @(a, b, cin), prevents missing a signal
    begin
      // in general it's best to use blocking assignments for combinational
      // logic specification
      p = a ^ b;            // blocking
      g = a & b;            // blocking
      s = p ^ cin;          // blocking
      cout = g | (p & cin); // blocking
    end

`ifdef  COCOTB_SIM 
initial
 begin
    $dumpfile("wave_sv.vcd");
    $dumpvars(
      0,
      a,
      b,
      cin,
      p,
      g,
      s,
      cout
    );
    #5;
 end
`endif

endmodule

hdl/4_23_fulladder/tests/wave_sv.vcd
$date
	Tue Sep 20 00:21:24 2022
$end
$version
	Icarus Verilog
$end
$timescale
	1ps
$end
$scope module fulladder $end
$var wire 1 ! a $end
$upscope $end
$scope module fulladder $end
$var wire 1 " b $end
$upscope $end
$scope module fulladder $end
$var wire 1 # cin $end
$upscope $end
$scope module fulladder $end
$var reg 1 $ p $end
$upscope $end
$scope module fulladder $end
$var reg 1 % g $end
$upscope $end
$scope module fulladder $end
$var reg 1 & s $end
$upscope $end
$scope module fulladder $end
$var reg 1 ' cout $end
$upscope $end
$enddefinitions $end
#0
$dumpvars
0'
0&
0%
0$
0#
0"
0!
$end
#1000
1&
1#
#2000
1$
1"
0#
#3000
1'
0&
1#
#4000
0'
1&
1!
0"
0#
#5000
1'
0&
1#
#6000
1%
0$
1"
0#
#7000
1&
1#
