hdl/4_33_signed_multiplier/hdl/vhdl/unsignedmult.vhd
library IEEE; use IEEE.STD_LOGIC_1164.all;
use IEEE.NUMERIC_STD_UNSIGNED.all;

entity unsignedmult is
	port (
	  a, b: in  STD_LOGIC_VECTOR(3 downto 0);
    y:    out STD_LOGIC_VECTOR(7 downto 0)
  );
end;

architecture synth of unsignedmult is
begin

  y <= a * b;

end;

hdl/4_33_unsigned_mult/tests/wave_sv.vcd
$date
	Thu Sep 29 14:52:05 2022
$end
$version
	Icarus Verilog
$end
$timescale
	1ps
$end
$scope module unsignedmult $end
$var wire 4 ! a [3:0] $end
$upscope $end
$scope module unsignedmult $end
$var wire 4 " b [3:0] $end
$upscope $end
$scope module unsignedmult $end
$var wire 8 # y [7:0] $end
$upscope $end
$enddefinitions $end
#0
$dumpvars
b0 #
b0 "
b0 !
$end
#1000
b1 "
#2000
b10 "
#3000
b11 "
#4000
b100 "
#5000
b101 "
#6000
b110 "
#7000
b111 "
#8000
b1000 "
#9000
b1001 "
#10000
b1010 "
#11000
b1011 "
#12000
b1100 "
#13000
b1101 "
#14000
b1110 "
#15000
b1111 "
#16000
b0 "
b0 #
b1 !
#17000
b1 #
b1 "
#18000
b10 #
b10 "
#19000
b11 #
b11 "
#20000
b100 #
b100 "
#21000
b101 #
b101 "
#22000
b110 #
b110 "
#23000
b111 #
b111 "
#24000
b1000 #
b1000 "
#25000
b1001 #
b1001 "
#26000
b1010 #
b1010 "
#27000
b1011 #
b1011 "
#28000
b1100 #
b1100 "
#29000
b1101 #
b1101 "
#30000
b1110 #
b1110 "
#31000
b1111 #
b1111 "
#32000
b0 "
b0 #
b10 !
#33000
b10 #
b1 "
#34000
b100 #
b10 "
#35000
b110 #
b11 "
#36000
b1000 #
b100 "
#37000
b1010 #
b101 "
#38000
b1100 #
b110 "
#39000
b1110 #
b111 "
#40000
b10000 #
b1000 "
#41000
b10010 #
b1001 "
#42000
b10100 #
b1010 "
#43000
b10110 #
b1011 "
#44000
b11000 #
b1100 "
#45000
b11010 #
b1101 "
#46000
b11100 #
b1110 "
#47000
b11110 #
b1111 "
#48000
b0 "
b0 #
b11 !
#49000
b11 #
b1 "
#50000
b110 #
b10 "
#51000
b1001 #
b11 "
#52000
b1100 #
b100 "
#53000
b1111 #
b101 "
#54000
b10010 #
b110 "
#55000
b10101 #
b111 "
#56000
b11000 #
b1000 "
#57000
b11011 #
b1001 "
#58000
b11110 #
b1010 "
#59000
b100001 #
b1011 "
#60000
b100100 #
b1100 "
#61000
b100111 #
b1101 "
#62000
b101010 #
b1110 "
#63000
b101101 #
b1111 "
#64000
b0 "
b0 #
b100 !
#65000
b100 #
b1 "
#66000
b1000 #
b10 "
#67000
b1100 #
b11 "
#68000
b10000 #
b100 "
#69000
b10100 #
b101 "
#70000
b11000 #
b110 "
#71000
b11100 #
b111 "
#72000
b100000 #
b1000 "
#73000
b100100 #
b1001 "
#74000
b101000 #
b1010 "
#75000
b101100 #
b1011 "
#76000
b110000 #
b1100 "
#77000
b110100 #
b1101 "
#78000
b111000 #
b1110 "
#79000
b111100 #
b1111 "
#80000
b0 "
b0 #
b101 !
#81000
b101 #
b1 "
#82000
b1010 #
b10 "
#83000
b1111 #
b11 "
#84000
b10100 #
b100 "
#85000
b11001 #
b101 "
#86000
b11110 #
b110 "
#87000
b100011 #
b111 "
#88000
b101000 #
b1000 "
#89000
b101101 #
b1001 "
#90000
b110010 #
b1010 "
#91000
b110111 #
b1011 "
#92000
b111100 #
b1100 "
#93000
b1000001 #
b1101 "
#94000
b1000110 #
b1110 "
#95000
b1001011 #
b1111 "
#96000
b0 "
b0 #
b110 !
#97000
b110 #
b1 "
#98000
b1100 #
b10 "
#99000
b10010 #
b11 "
#100000
b11000 #
b100 "
#101000
b11110 #
b101 "
#102000
b100100 #
b110 "
#103000
b101010 #
b111 "
#104000
b110000 #
b1000 "
#105000
b110110 #
b1001 "
#106000
b111100 #
b1010 "
#107000
b1000010 #
b1011 "
#108000
b1001000 #
b1100 "
#109000
b1001110 #
b1101 "
#110000
b1010100 #
b1110 "
#111000
b1011010 #
b1111 "
#112000
b0 "
b0 #
b111 !
#113000
b111 #
b1 "
#114000
b1110 #
b10 "
#115000
b10101 #
b11 "
#116000
b11100 #
b100 "
#117000
b100011 #
b101 "
#118000
b101010 #
b110 "
#119000
b110001 #
b111 "
#120000
b111000 #
b1000 "
#121000
b111111 #
b1001 "
#122000
b1000110 #
b1010 "
#123000
b1001101 #
b1011 "
#124000
b1010100 #
b1100 "
#125000
b1011011 #
b1101 "
#126000
b1100010 #
b1110 "
#127000
b1101001 #
b1111 "
#128000
b0 "
b0 #
b1000 !
#129000
b1000 #
b1 "
#130000
b10000 #
b10 "
#131000
b11000 #
b11 "
#132000
b100000 #
b100 "
#133000
b101000 #
b101 "
#134000
b110000 #
b110 "
#135000
b111000 #
b111 "
#136000
b1000000 #
b1000 "
#137000
b1001000 #
b1001 "
#138000
b1010000 #
b1010 "
#139000
b1011000 #
b1011 "
#140000
b1100000 #
b1100 "
#141000
b1101000 #
b1101 "
#142000
b1110000 #
b1110 "
#143000
b1111000 #
b1111 "
#144000
b0 "
b0 #
b1001 !
#145000
b1001 #
b1 "
#146000
b10010 #
b10 "
#147000
b11011 #
b11 "
#148000
b100100 #
b100 "
#149000
b101101 #
b101 "
#150000
b110110 #
b110 "
#151000
b111111 #
b111 "
#152000
b1001000 #
b1000 "
#153000
b1010001 #
b1001 "
#154000
b1011010 #
b1010 "
#155000
b1100011 #
b1011 "
#156000
b1101100 #
b1100 "
#157000
b1110101 #
b1101 "
#158000
b1111110 #
b1110 "
#159000
b10000111 #
b1111 "
#160000
b0 "
b0 #
b1010 !
#161000
b1010 #
b1 "
#162000
b10100 #
b10 "
#163000
b11110 #
b11 "
#164000
b101000 #
b100 "
#165000
b110010 #
b101 "
#166000
b111100 #
b110 "
#167000
b1000110 #
b111 "
#168000
b1010000 #
b1000 "
#169000
b1011010 #
b1001 "
#170000
b1100100 #
b1010 "
#171000
b1101110 #
b1011 "
#172000
b1111000 #
b1100 "
#173000
b10000010 #
b1101 "
#174000
b10001100 #
b1110 "
#175000
b10010110 #
b1111 "
#176000
b0 "
b0 #
b1011 !
#177000
b1011 #
b1 "
#178000
b10110 #
b10 "
#179000
b100001 #
b11 "
#180000
b101100 #
b100 "
#181000
b110111 #
b101 "
#182000
b1000010 #
b110 "
#183000
b1001101 #
b111 "
#184000
b1011000 #
b1000 "
#185000
b1100011 #
b1001 "
#186000
b1101110 #
b1010 "
#187000
b1111001 #
b1011 "
#188000
b10000100 #
b1100 "
#189000
b10001111 #
b1101 "
#190000
b10011010 #
b1110 "
#191000
b10100101 #
b1111 "
#192000
b0 "
b0 #
b1100 !
#193000
b1100 #
b1 "
#194000
b11000 #
b10 "
#195000
b100100 #
b11 "
#196000
b110000 #
b100 "
#197000
b111100 #
b101 "
#198000
b1001000 #
b110 "
#199000
b1010100 #
b111 "
#200000
b1100000 #
b1000 "
#201000
b1101100 #
b1001 "
#202000
b1111000 #
b1010 "
#203000
b10000100 #
b1011 "
#204000
b10010000 #
b1100 "
#205000
b10011100 #
b1101 "
#206000
b10101000 #
b1110 "
#207000
b10110100 #
b1111 "
#208000
b0 "
b0 #
b1101 !
#209000
b1101 #
b1 "
#210000
b11010 #
b10 "
#211000
b100111 #
b11 "
#212000
b110100 #
b100 "
#213000
b1000001 #
b101 "
#214000
b1001110 #
b110 "
#215000
b1011011 #
b111 "
#216000
b1101000 #
b1000 "
#217000
b1110101 #
b1001 "
#218000
b10000010 #
b1010 "
#219000
b10001111 #
b1011 "
#220000
b10011100 #
b1100 "
#221000
b10101001 #
b1101 "
#222000
b10110110 #
b1110 "
#223000
b11000011 #
b1111 "
#224000
b0 "
b0 #
b1110 !
#225000
b1110 #
b1 "
#226000
b11100 #
b10 "
#227000
b101010 #
b11 "
#228000
b111000 #
b100 "
#229000
b1000110 #
b101 "
#230000
b1010100 #
b110 "
#231000
b1100010 #
b111 "
#232000
b1110000 #
b1000 "
#233000
b1111110 #
b1001 "
#234000
b10001100 #
b1010 "
#235000
b10011010 #
b1011 "
#236000
b10101000 #
b1100 "
#237000
b10110110 #
b1101 "
#238000
b11000100 #
b1110 "
#239000
b11010010 #
b1111 "
#240000
b0 "
b0 #
b1111 !
#241000
b1111 #
b1 "
#242000
b11110 #
b10 "
#243000
b101101 #
b11 "
#244000
b111100 #
b100 "
#245000
b1001011 #
b101 "
#246000
b1011010 #
b110 "
#247000
b1101001 #
b111 "
#248000
b1111000 #
b1000 "
#249000
b10000111 #
b1001 "
#250000
b10010110 #
b1010 "
#251000
b10100101 #
b1011 "
#252000
b10110100 #
b1100 "
#253000
b11000011 #
b1101 "
#254000
b11010010 #
b1110 "
#255000
b11100001 #
b1111 "
