hdl/4_33_signed_multiplier/hdl/vhdl/unsignedmult.vhd
library IEEE; use IEEE.STD_LOGIC_1164.all;
use IEEE.NUMERIC_STD_UNSIGNED.all;

entity unsignedmult is
	port (
	  a, b: in  STD_LOGIC_VECTOR(3 downto 0);
    y:    out STD_LOGIC_VECTOR(7 downto 0)
  );
end;

architecture synth of unsignedmult is
begin

  y <= a * b;

end;

hdl/4_33_unsigned_mult/tests/wave_vhdl.vcd
$date
  Thu Sep 22 02:18:11 2022
$end
$version
  GHDL v0
$end
$timescale
  1 fs
$end
$scope module standard $end
$upscope $end
$scope module textio $end
$upscope $end
$scope module std_logic_1164 $end
$upscope $end
$scope module numeric_std_unsigned $end
$upscope $end
$scope module numeric_std $end
$upscope $end
$scope module unsignedmult $end
$var reg 4 ! a[3:0] $end
$var reg 4 " b[3:0] $end
$var reg 8 # y[7:0] $end
$upscope $end
$enddefinitions $end
#0
b0000 !
b0000 "
b00000000 #
#1000000
b0001 "
#2000000
b0010 "
#3000000
b0011 "
#4000000
b0100 "
#5000000
b0101 "
#6000000
b0110 "
#7000000
b0111 "
#8000000
b1000 "
#9000000
b1001 "
#10000000
b1010 "
#11000000
b1011 "
#12000000
b1100 "
#13000000
b1101 "
#14000000
b1110 "
#15000000
b1111 "
#16000000
b0001 !
b0000 "
#17000000
b0001 "
b00000001 #
#18000000
b0010 "
b00000010 #
#19000000
b0011 "
b00000011 #
#20000000
b0100 "
b00000100 #
#21000000
b0101 "
b00000101 #
#22000000
b0110 "
b00000110 #
#23000000
b0111 "
b00000111 #
#24000000
b1000 "
b00001000 #
#25000000
b1001 "
b00001001 #
#26000000
b1010 "
b00001010 #
#27000000
b1011 "
b00001011 #
#28000000
b1100 "
b00001100 #
#29000000
b1101 "
b00001101 #
#30000000
b1110 "
b00001110 #
#31000000
b1111 "
b00001111 #
#32000000
b0010 !
b0000 "
b00000000 #
#33000000
b0001 "
b00000010 #
#34000000
b0010 "
b00000100 #
#35000000
b0011 "
b00000110 #
#36000000
b0100 "
b00001000 #
#37000000
b0101 "
b00001010 #
#38000000
b0110 "
b00001100 #
#39000000
b0111 "
b00001110 #
#40000000
b1000 "
b00010000 #
#41000000
b1001 "
b00010010 #
#42000000
b1010 "
b00010100 #
#43000000
b1011 "
b00010110 #
#44000000
b1100 "
b00011000 #
#45000000
b1101 "
b00011010 #
#46000000
b1110 "
b00011100 #
#47000000
b1111 "
b00011110 #
#48000000
b0011 !
b0000 "
b00000000 #
#49000000
b0001 "
b00000011 #
#50000000
b0010 "
b00000110 #
#51000000
b0011 "
b00001001 #
#52000000
b0100 "
b00001100 #
#53000000
b0101 "
b00001111 #
#54000000
b0110 "
b00010010 #
#55000000
b0111 "
b00010101 #
#56000000
b1000 "
b00011000 #
#57000000
b1001 "
b00011011 #
#58000000
b1010 "
b00011110 #
#59000000
b1011 "
b00100001 #
#60000000
b1100 "
b00100100 #
#61000000
b1101 "
b00100111 #
#62000000
b1110 "
b00101010 #
#63000000
b1111 "
b00101101 #
#64000000
b0100 !
b0000 "
b00000000 #
#65000000
b0001 "
b00000100 #
#66000000
b0010 "
b00001000 #
#67000000
b0011 "
b00001100 #
#68000000
b0100 "
b00010000 #
#69000000
b0101 "
b00010100 #
#70000000
b0110 "
b00011000 #
#71000000
b0111 "
b00011100 #
#72000000
b1000 "
b00100000 #
#73000000
b1001 "
b00100100 #
#74000000
b1010 "
b00101000 #
#75000000
b1011 "
b00101100 #
#76000000
b1100 "
b00110000 #
#77000000
b1101 "
b00110100 #
#78000000
b1110 "
b00111000 #
#79000000
b1111 "
b00111100 #
#80000000
b0101 !
b0000 "
b00000000 #
#81000000
b0001 "
b00000101 #
#82000000
b0010 "
b00001010 #
#83000000
b0011 "
b00001111 #
#84000000
b0100 "
b00010100 #
#85000000
b0101 "
b00011001 #
#86000000
b0110 "
b00011110 #
#87000000
b0111 "
b00100011 #
#88000000
b1000 "
b00101000 #
#89000000
b1001 "
b00101101 #
#90000000
b1010 "
b00110010 #
#91000000
b1011 "
b00110111 #
#92000000
b1100 "
b00111100 #
#93000000
b1101 "
b01000001 #
#94000000
b1110 "
b01000110 #
#95000000
b1111 "
b01001011 #
#96000000
b0110 !
b0000 "
b00000000 #
#97000000
b0001 "
b00000110 #
#98000000
b0010 "
b00001100 #
#99000000
b0011 "
b00010010 #
#100000000
b0100 "
b00011000 #
#101000000
b0101 "
b00011110 #
#102000000
b0110 "
b00100100 #
#103000000
b0111 "
b00101010 #
#104000000
b1000 "
b00110000 #
#105000000
b1001 "
b00110110 #
#106000000
b1010 "
b00111100 #
#107000000
b1011 "
b01000010 #
#108000000
b1100 "
b01001000 #
#109000000
b1101 "
b01001110 #
#110000000
b1110 "
b01010100 #
#111000000
b1111 "
b01011010 #
#112000000
b0111 !
b0000 "
b00000000 #
#113000000
b0001 "
b00000111 #
#114000000
b0010 "
b00001110 #
#115000000
b0011 "
b00010101 #
#116000000
b0100 "
b00011100 #
#117000000
b0101 "
b00100011 #
#118000000
b0110 "
b00101010 #
#119000000
b0111 "
b00110001 #
#120000000
b1000 "
b00111000 #
#121000000
b1001 "
b00111111 #
#122000000
b1010 "
b01000110 #
#123000000
b1011 "
b01001101 #
#124000000
b1100 "
b01010100 #
#125000000
b1101 "
b01011011 #
#126000000
b1110 "
b01100010 #
#127000000
b1111 "
b01101001 #
#128000000
b1000 !
b0000 "
b00000000 #
#129000000
b0001 "
b00001000 #
#130000000
b0010 "
b00010000 #
#131000000
b0011 "
b00011000 #
#132000000
b0100 "
b00100000 #
#133000000
b0101 "
b00101000 #
#134000000
b0110 "
b00110000 #
#135000000
b0111 "
b00111000 #
#136000000
b1000 "
b01000000 #
#137000000
b1001 "
b01001000 #
#138000000
b1010 "
b01010000 #
#139000000
b1011 "
b01011000 #
#140000000
b1100 "
b01100000 #
#141000000
b1101 "
b01101000 #
#142000000
b1110 "
b01110000 #
#143000000
b1111 "
b01111000 #
#144000000
b1001 !
b0000 "
b00000000 #
#145000000
b0001 "
b00001001 #
#146000000
b0010 "
b00010010 #
#147000000
b0011 "
b00011011 #
#148000000
b0100 "
b00100100 #
#149000000
b0101 "
b00101101 #
#150000000
b0110 "
b00110110 #
#151000000
b0111 "
b00111111 #
#152000000
b1000 "
b01001000 #
#153000000
b1001 "
b01010001 #
#154000000
b1010 "
b01011010 #
#155000000
b1011 "
b01100011 #
#156000000
b1100 "
b01101100 #
#157000000
b1101 "
b01110101 #
#158000000
b1110 "
b01111110 #
#159000000
b1111 "
b10000111 #
#160000000
b1010 !
b0000 "
b00000000 #
#161000000
b0001 "
b00001010 #
#162000000
b0010 "
b00010100 #
#163000000
b0011 "
b00011110 #
#164000000
b0100 "
b00101000 #
#165000000
b0101 "
b00110010 #
#166000000
b0110 "
b00111100 #
#167000000
b0111 "
b01000110 #
#168000000
b1000 "
b01010000 #
#169000000
b1001 "
b01011010 #
#170000000
b1010 "
b01100100 #
#171000000
b1011 "
b01101110 #
#172000000
b1100 "
b01111000 #
#173000000
b1101 "
b10000010 #
#174000000
b1110 "
b10001100 #
#175000000
b1111 "
b10010110 #
#176000000
b1011 !
b0000 "
b00000000 #
#177000000
b0001 "
b00001011 #
#178000000
b0010 "
b00010110 #
#179000000
b0011 "
b00100001 #
#180000000
b0100 "
b00101100 #
#181000000
b0101 "
b00110111 #
#182000000
b0110 "
b01000010 #
#183000000
b0111 "
b01001101 #
#184000000
b1000 "
b01011000 #
#185000000
b1001 "
b01100011 #
#186000000
b1010 "
b01101110 #
#187000000
b1011 "
b01111001 #
#188000000
b1100 "
b10000100 #
#189000000
b1101 "
b10001111 #
#190000000
b1110 "
b10011010 #
#191000000
b1111 "
b10100101 #
#192000000
b1100 !
b0000 "
b00000000 #
#193000000
b0001 "
b00001100 #
#194000000
b0010 "
b00011000 #
#195000000
b0011 "
b00100100 #
#196000000
b0100 "
b00110000 #
#197000000
b0101 "
b00111100 #
#198000000
b0110 "
b01001000 #
#199000000
b0111 "
b01010100 #
#200000000
b1000 "
b01100000 #
#201000000
b1001 "
b01101100 #
#202000000
b1010 "
b01111000 #
#203000000
b1011 "
b10000100 #
#204000000
b1100 "
b10010000 #
#205000000
b1101 "
b10011100 #
#206000000
b1110 "
b10101000 #
#207000000
b1111 "
b10110100 #
#208000000
b1101 !
b0000 "
b00000000 #
#209000000
b0001 "
b00001101 #
#210000000
b0010 "
b00011010 #
#211000000
b0011 "
b00100111 #
#212000000
b0100 "
b00110100 #
#213000000
b0101 "
b01000001 #
#214000000
b0110 "
b01001110 #
#215000000
b0111 "
b01011011 #
#216000000
b1000 "
b01101000 #
#217000000
b1001 "
b01110101 #
#218000000
b1010 "
b10000010 #
#219000000
b1011 "
b10001111 #
#220000000
b1100 "
b10011100 #
#221000000
b1101 "
b10101001 #
#222000000
b1110 "
b10110110 #
#223000000
b1111 "
b11000011 #
#224000000
b1110 !
b0000 "
b00000000 #
#225000000
b0001 "
b00001110 #
#226000000
b0010 "
b00011100 #
#227000000
b0011 "
b00101010 #
#228000000
b0100 "
b00111000 #
#229000000
b0101 "
b01000110 #
#230000000
b0110 "
b01010100 #
#231000000
b0111 "
b01100010 #
#232000000
b1000 "
b01110000 #
#233000000
b1001 "
b01111110 #
#234000000
b1010 "
b10001100 #
#235000000
b1011 "
b10011010 #
#236000000
b1100 "
b10101000 #
#237000000
b1101 "
b10110110 #
#238000000
b1110 "
b11000100 #
#239000000
b1111 "
b11010010 #
#240000000
b1111 !
b0000 "
b00000000 #
#241000000
b0001 "
b00001111 #
#242000000
b0010 "
b00011110 #
#243000000
b0011 "
b00101101 #
#244000000
b0100 "
b00111100 #
#245000000
b0101 "
b01001011 #
#246000000
b0110 "
b01011010 #
#247000000
b0111 "
b01101001 #
#248000000
b1000 "
b01111000 #
#249000000
b1001 "
b10000111 #
#250000000
b1010 "
b10010110 #
#251000000
b1011 "
b10100101 #
#252000000
b1100 "
b10110100 #
#253000000
b1101 "
b11000011 #
#254000000
b1110 "
b11010010 #
#255000000
b1111 "
b11100001 #
