hdl/4_24_seven_segment/hdl/vhdl/sevenseg.vhd
library IEEE; use IEEE.STD_LOGIC_1164.all;

entity sevenseg is
	port (
		data:     in  STD_LOGIC_VECTOR(3 downto 0);
		segments: out STD_LOGIC_VECTOR(6 downto 0)
	);
end;

architecture synth of sevenseg is
begin
  process(all)
  begin
    case data is -- can appear outside processes, so less of a reason to need
                 -- a process statement here to describe combinational logic
      when X"0" => segments <= "1111110";
      when X"1" => segments <= "0110000";
      when X"2" => segments <= "1101101";
      when X"3" => segments <= "1111001";
      when X"4" => segments <= "0110011";
      when X"5" => segments <= "1011011";
      when X"6" => segments <= "1011111";
      when X"7" => segments <= "1110000";
      when X"8" => segments <= "1111111";
      when X"9" => segments <= "1110011";
      when others => segments <= (others => '0');
    end case;
  end process;
end;

hdl/4_24_seven_segment/tests/wave_vhdl.vcd
$date
  Tue Sep 20 00:43:46 2022
$end
$version
  GHDL v0
$end
$timescale
  1 fs
$end
$scope module standard $end
$upscope $end
$scope module textio $end
$upscope $end
$scope module std_logic_1164 $end
$upscope $end
$scope module sevenseg $end
$var reg 4 ! data[3:0] $end
$var reg 7 " segments[6:0] $end
$upscope $end
$enddefinitions $end
#0
b0000 !
b1111110 "
#1000000
b0001 !
b0110000 "
#2000000
b0010 !
b1101101 "
#3000000
b0011 !
b1111001 "
#4000000
b0100 !
b0110011 "
#5000000
b0101 !
b1011011 "
#6000000
b0110 !
b1011111 "
#7000000
b0111 !
b1110000 "
#8000000
b1000 !
b1111111 "
#9000000
b1001 !
b1110011 "
#10000000
b1010 !
b0000000 "
#11000000
b1011 !
#12000000
b1100 !
#13000000
b1101 !
#14000000
b1110 !
#15000000
b1111 !
