hdl/4_31_moore/hdl/vhdl/moore.vhd
library IEEE; use IEEE.STD_LOGIC_1164.all;

entity moore is
	port (
		clk, reset:     in  STD_LOGIC;
    a:              in  STD_LOGIC;
    y:              out STD_LOGIC
	);
end;

architecture synth of moore is
  type statetype is (S0, S1, S2);
  signal state, nextstate: statetype;
begin

  -- state register
  process (clk, reset) begin
    if reset then
      state <= S0;
    elsif rising_edge(clk) then
      state <= nextstate;
    end if;
  end process;

  -- next state logic
  process (all) begin
    case state is
      when S0 =>
        if a then
          nextstate <= S0;
        else 
          nextstate <= S1;
        end if;
      when S1 =>
        if a then
          nextstate <= S2;
        else
          nextstate <= S1;
        end if;
      when S2 =>
        if a then
          nextstate <= S0;
        else
          nextstate <= S1;
        end if;
      when others =>
        nextstate <= S0;
    end case;
  end process;

  -- output logic
  y <= '1' when state = S2 else '0';


end;

hdl/4_31_moore/tests/wave_vhdl.vcd
$date
  Thu Sep 22 01:36:08 2022
$end
$version
  GHDL v0
$end
$timescale
  1 fs
$end
$scope module standard $end
$upscope $end
$scope module textio $end
$upscope $end
$scope module std_logic_1164 $end
$upscope $end
$scope module moore $end
$var reg 1 ! clk $end
$var reg 1 " reset $end
$var reg 1 # a $end
$var reg 1 $ y $end
$comment state is not handled $end
$comment nextstate is not handled $end
$upscope $end
$enddefinitions $end
#0
1!
U"
U#
0$
#5000000000
0!
1"
#10000000000
1!
#15000000000
0!
0"
1#
#20000000000
1!
#25000000000
0!
#30000000000
1!
#35000000000
0!
0#
#40000000000
1!
#45000000000
0!
1#
#50000000000
1!
1$
#55000000000
0!
#60000000000
1!
0$
#65000000000
0!
#70000000000
1!
#75000000000
0!
0#
#80000000000
1!
#85000000000
0!
1#
#90000000000
1!
1$
#95000000000
0!
0#
#100000000000
1!
0$
#105000000000
0!
#110000000000
1!
#115000000000
0!
1#
#120000000000
1!
1$
#125000000000
0!
0#
#130000000000
1!
0$
#135000000000
0!
#140000000000
1!
#145000000000
0!
1#
#150000000000
1!
1$
#155000000000
0!
#160000000000
1!
0$
#165000000000
0!
0#
#170000000000
1!
#175000000000
0!
#180000000000
1!
#185000000000
0!
1#
#190000000000
1!
1$
#195000000000
0!
#200000000000
1!
0$
#205000000000
0!
#210000000000
1!
#215000000000
0!
0#
#220000000000
1!
#225000000000
0!
1#
#230000000000
1!
1$
#235000000000
0!
#240000000000
1!
0$
#245000000000
0!
#250000000000
1!
#255000000000
0!
0#
#260000000000
1!
#265000000000
0!
#270000000000
1!
#275000000000
0!
#280000000000
1!
#285000000000
0!
1#
#290000000000
1!
1$
#295000000000
0!
#300000000000
1!
0$
#305000000000
0!
#310000000000
1!
#315000000000
0!
0#
