hdl/4_33_signed_mult/hdl/vhdl/unsignedmult.vhd
library IEEE; use IEEE.STD_LOGIC_1164.all;
use IEEE.NUMERIC_STD.all;

entity signedmult is
	port (
	  a, b: in  SIGNED(3 downto 0);
    y:    out SIGNED(7 downto 0)
  );
end;

architecture synth of signedmult is
begin

  y <= a * b;

end;

hdl/4_33_signed_mult/tests/wave_vhdl.vcd
$date
  Thu Sep 22 03:27:09 2022
$end
$version
  GHDL v0
$end
$timescale
  1 fs
$end
$scope module standard $end
$upscope $end
$scope module textio $end
$upscope $end
$scope module std_logic_1164 $end
$upscope $end
$scope module numeric_std $end
$upscope $end
$scope module signedmult $end
$var reg 4 ! a[3:0] $end
$var reg 4 " b[3:0] $end
$var reg 8 # y[7:0] $end
$upscope $end
$enddefinitions $end
#0
b1000 !
b1000 "
b01000000 #
#1000000
b1001 "
b00111000 #
#2000000
b1010 "
b00110000 #
#3000000
b1011 "
b00101000 #
#4000000
b1100 "
b00100000 #
#5000000
b1101 "
b00011000 #
#6000000
b1110 "
b00010000 #
#7000000
b1111 "
b00001000 #
#8000000
b0000 "
b00000000 #
#9000000
b0001 "
b11111000 #
#10000000
b0010 "
b11110000 #
#11000000
b0011 "
b11101000 #
#12000000
b0100 "
b11100000 #
#13000000
b0101 "
b11011000 #
#14000000
b0110 "
b11010000 #
#15000000
b0111 "
b11001000 #
#16000000
b1001 !
b1000 "
b00111000 #
#17000000
b1001 "
b00110001 #
#18000000
b1010 "
b00101010 #
#19000000
b1011 "
b00100011 #
#20000000
b1100 "
b00011100 #
#21000000
b1101 "
b00010101 #
#22000000
b1110 "
b00001110 #
#23000000
b1111 "
b00000111 #
#24000000
b0000 "
b00000000 #
#25000000
b0001 "
b11111001 #
#26000000
b0010 "
b11110010 #
#27000000
b0011 "
b11101011 #
#28000000
b0100 "
b11100100 #
#29000000
b0101 "
b11011101 #
#30000000
b0110 "
b11010110 #
#31000000
b0111 "
b11001111 #
#32000000
b1010 !
b1000 "
b00110000 #
#33000000
b1001 "
b00101010 #
#34000000
b1010 "
b00100100 #
#35000000
b1011 "
b00011110 #
#36000000
b1100 "
b00011000 #
#37000000
b1101 "
b00010010 #
#38000000
b1110 "
b00001100 #
#39000000
b1111 "
b00000110 #
#40000000
b0000 "
b00000000 #
#41000000
b0001 "
b11111010 #
#42000000
b0010 "
b11110100 #
#43000000
b0011 "
b11101110 #
#44000000
b0100 "
b11101000 #
#45000000
b0101 "
b11100010 #
#46000000
b0110 "
b11011100 #
#47000000
b0111 "
b11010110 #
#48000000
b1011 !
b1000 "
b00101000 #
#49000000
b1001 "
b00100011 #
#50000000
b1010 "
b00011110 #
#51000000
b1011 "
b00011001 #
#52000000
b1100 "
b00010100 #
#53000000
b1101 "
b00001111 #
#54000000
b1110 "
b00001010 #
#55000000
b1111 "
b00000101 #
#56000000
b0000 "
b00000000 #
#57000000
b0001 "
b11111011 #
#58000000
b0010 "
b11110110 #
#59000000
b0011 "
b11110001 #
#60000000
b0100 "
b11101100 #
#61000000
b0101 "
b11100111 #
#62000000
b0110 "
b11100010 #
#63000000
b0111 "
b11011101 #
#64000000
b1100 !
b1000 "
b00100000 #
#65000000
b1001 "
b00011100 #
#66000000
b1010 "
b00011000 #
#67000000
b1011 "
b00010100 #
#68000000
b1100 "
b00010000 #
#69000000
b1101 "
b00001100 #
#70000000
b1110 "
b00001000 #
#71000000
b1111 "
b00000100 #
#72000000
b0000 "
b00000000 #
#73000000
b0001 "
b11111100 #
#74000000
b0010 "
b11111000 #
#75000000
b0011 "
b11110100 #
#76000000
b0100 "
b11110000 #
#77000000
b0101 "
b11101100 #
#78000000
b0110 "
b11101000 #
#79000000
b0111 "
b11100100 #
#80000000
b1101 !
b1000 "
b00011000 #
#81000000
b1001 "
b00010101 #
#82000000
b1010 "
b00010010 #
#83000000
b1011 "
b00001111 #
#84000000
b1100 "
b00001100 #
#85000000
b1101 "
b00001001 #
#86000000
b1110 "
b00000110 #
#87000000
b1111 "
b00000011 #
#88000000
b0000 "
b00000000 #
#89000000
b0001 "
b11111101 #
#90000000
b0010 "
b11111010 #
#91000000
b0011 "
b11110111 #
#92000000
b0100 "
b11110100 #
#93000000
b0101 "
b11110001 #
#94000000
b0110 "
b11101110 #
#95000000
b0111 "
b11101011 #
#96000000
b1110 !
b1000 "
b00010000 #
#97000000
b1001 "
b00001110 #
#98000000
b1010 "
b00001100 #
#99000000
b1011 "
b00001010 #
#100000000
b1100 "
b00001000 #
#101000000
b1101 "
b00000110 #
#102000000
b1110 "
b00000100 #
#103000000
b1111 "
b00000010 #
#104000000
b0000 "
b00000000 #
#105000000
b0001 "
b11111110 #
#106000000
b0010 "
b11111100 #
#107000000
b0011 "
b11111010 #
#108000000
b0100 "
b11111000 #
#109000000
b0101 "
b11110110 #
#110000000
b0110 "
b11110100 #
#111000000
b0111 "
b11110010 #
#112000000
b1111 !
b1000 "
b00001000 #
#113000000
b1001 "
b00000111 #
#114000000
b1010 "
b00000110 #
#115000000
b1011 "
b00000101 #
#116000000
b1100 "
b00000100 #
#117000000
b1101 "
b00000011 #
#118000000
b1110 "
b00000010 #
#119000000
b1111 "
b00000001 #
#120000000
b0000 "
b00000000 #
#121000000
b0001 "
b11111111 #
#122000000
b0010 "
b11111110 #
#123000000
b0011 "
b11111101 #
#124000000
b0100 "
b11111100 #
#125000000
b0101 "
b11111011 #
#126000000
b0110 "
b11111010 #
#127000000
b0111 "
b11111001 #
#128000000
b0000 !
b1000 "
b00000000 #
#129000000
b1001 "
#130000000
b1010 "
#131000000
b1011 "
#132000000
b1100 "
#133000000
b1101 "
#134000000
b1110 "
#135000000
b1111 "
#136000000
b0000 "
#137000000
b0001 "
#138000000
b0010 "
#139000000
b0011 "
#140000000
b0100 "
#141000000
b0101 "
#142000000
b0110 "
#143000000
b0111 "
#144000000
b0001 !
b1000 "
b11111000 #
#145000000
b1001 "
b11111001 #
#146000000
b1010 "
b11111010 #
#147000000
b1011 "
b11111011 #
#148000000
b1100 "
b11111100 #
#149000000
b1101 "
b11111101 #
#150000000
b1110 "
b11111110 #
#151000000
b1111 "
b11111111 #
#152000000
b0000 "
b00000000 #
#153000000
b0001 "
b00000001 #
#154000000
b0010 "
b00000010 #
#155000000
b0011 "
b00000011 #
#156000000
b0100 "
b00000100 #
#157000000
b0101 "
b00000101 #
#158000000
b0110 "
b00000110 #
#159000000
b0111 "
b00000111 #
#160000000
b0010 !
b1000 "
b11110000 #
#161000000
b1001 "
b11110010 #
#162000000
b1010 "
b11110100 #
#163000000
b1011 "
b11110110 #
#164000000
b1100 "
b11111000 #
#165000000
b1101 "
b11111010 #
#166000000
b1110 "
b11111100 #
#167000000
b1111 "
b11111110 #
#168000000
b0000 "
b00000000 #
#169000000
b0001 "
b00000010 #
#170000000
b0010 "
b00000100 #
#171000000
b0011 "
b00000110 #
#172000000
b0100 "
b00001000 #
#173000000
b0101 "
b00001010 #
#174000000
b0110 "
b00001100 #
#175000000
b0111 "
b00001110 #
#176000000
b0011 !
b1000 "
b11101000 #
#177000000
b1001 "
b11101011 #
#178000000
b1010 "
b11101110 #
#179000000
b1011 "
b11110001 #
#180000000
b1100 "
b11110100 #
#181000000
b1101 "
b11110111 #
#182000000
b1110 "
b11111010 #
#183000000
b1111 "
b11111101 #
#184000000
b0000 "
b00000000 #
#185000000
b0001 "
b00000011 #
#186000000
b0010 "
b00000110 #
#187000000
b0011 "
b00001001 #
#188000000
b0100 "
b00001100 #
#189000000
b0101 "
b00001111 #
#190000000
b0110 "
b00010010 #
#191000000
b0111 "
b00010101 #
#192000000
b0100 !
b1000 "
b11100000 #
#193000000
b1001 "
b11100100 #
#194000000
b1010 "
b11101000 #
#195000000
b1011 "
b11101100 #
#196000000
b1100 "
b11110000 #
#197000000
b1101 "
b11110100 #
#198000000
b1110 "
b11111000 #
#199000000
b1111 "
b11111100 #
#200000000
b0000 "
b00000000 #
#201000000
b0001 "
b00000100 #
#202000000
b0010 "
b00001000 #
#203000000
b0011 "
b00001100 #
#204000000
b0100 "
b00010000 #
#205000000
b0101 "
b00010100 #
#206000000
b0110 "
b00011000 #
#207000000
b0111 "
b00011100 #
#208000000
b0101 !
b1000 "
b11011000 #
#209000000
b1001 "
b11011101 #
#210000000
b1010 "
b11100010 #
#211000000
b1011 "
b11100111 #
#212000000
b1100 "
b11101100 #
#213000000
b1101 "
b11110001 #
#214000000
b1110 "
b11110110 #
#215000000
b1111 "
b11111011 #
#216000000
b0000 "
b00000000 #
#217000000
b0001 "
b00000101 #
#218000000
b0010 "
b00001010 #
#219000000
b0011 "
b00001111 #
#220000000
b0100 "
b00010100 #
#221000000
b0101 "
b00011001 #
#222000000
b0110 "
b00011110 #
#223000000
b0111 "
b00100011 #
#224000000
b0110 !
b1000 "
b11010000 #
#225000000
b1001 "
b11010110 #
#226000000
b1010 "
b11011100 #
#227000000
b1011 "
b11100010 #
#228000000
b1100 "
b11101000 #
#229000000
b1101 "
b11101110 #
#230000000
b1110 "
b11110100 #
#231000000
b1111 "
b11111010 #
#232000000
b0000 "
b00000000 #
#233000000
b0001 "
b00000110 #
#234000000
b0010 "
b00001100 #
#235000000
b0011 "
b00010010 #
#236000000
b0100 "
b00011000 #
#237000000
b0101 "
b00011110 #
#238000000
b0110 "
b00100100 #
#239000000
b0111 "
b00101010 #
#240000000
b0111 !
b1000 "
b11001000 #
#241000000
b1001 "
b11001111 #
#242000000
b1010 "
b11010110 #
#243000000
b1011 "
b11011101 #
#244000000
b1100 "
b11100100 #
#245000000
b1101 "
b11101011 #
#246000000
b1110 "
b11110010 #
#247000000
b1111 "
b11111001 #
#248000000
b0000 "
b00000000 #
#249000000
b0001 "
b00000111 #
#250000000
b0010 "
b00001110 #
#251000000
b0011 "
b00010101 #
#252000000
b0100 "
b00011100 #
#253000000
b0101 "
b00100011 #
#254000000
b0110 "
b00101010 #
#255000000
b0111 "
b00110001 #
