hdl/4_07_fulladder/hdl/sv/fulladder.sv
module fulladder (
	input   logic a, b, cin,
	output  logic s, cout
);

	logic p, g;

	assign p = a ^ b;
	assign g = a & b;

	assign s = p ^ cin;
	assign cout = g | (p & cin);

endmodule

hdl/4_07_fulladder/tests/wave_vhdl.vcd
$date
  Tue Sep 20 14:45:19 2022
$end
$version
  GHDL v0
$end
$timescale
  1 fs
$end
$scope module standard $end
$upscope $end
$scope module textio $end
$upscope $end
$scope module std_logic_1164 $end
$upscope $end
$scope module fulladder $end
$var reg 1 ! a $end
$var reg 1 " b $end
$var reg 1 # cin $end
$var reg 1 $ s $end
$var reg 1 % cout $end
$var reg 1 & p $end
$var reg 1 ' g $end
$upscope $end
$enddefinitions $end
#0
0!
0"
0#
0$
0%
0&
0'
#1000000
1#
1$
#2000000
1"
0#
1$
1&
#3000000
1#
0$
1%
#4000000
1!
0"
0#
1$
0%
#5000000
1#
0$
1%
#6000000
1"
0#
0$
1%
0&
1'
#7000000
1#
1$
