hdl/4_10_tristate/hdl/vhdl/tristate.vhd
library IEEE; use IEEE.STD_LOGIC_1164.all;

entity tristate is
	port (
		a: in STD_LOGIC_VECTOR(3 downto 0);
		en: in STD_LOGIC;
		y: out STD_LOGIC_VECTOR(3 downto 0)
	);
end;

architecture synth of tristate is
begin
	y <= a when en = '1' else "ZZZZ";
end;

hdl/4_15_structural_mux2/hdl/sv/mux2.sv
module mux2 (
	input   logic [3:0] d0, d1,
  input   logic       s,
  output  tri   [3:0] y
);

tristate t0 (
  d0, ~s, y
);

tristate t1 (
  d1, s, y
);

`ifdef  COCOTB_SIM 
initial
 begin
    $dumpfile("wave_sv.vcd");
    $dumpvars(
      0,
      d0, d1,
      s,
      y
    );
    #5;
 end
 `endif

endmodule

hdl/4_15_structural_mux2/tests/wave_sv.vcd
$date
	Thu Sep 29 14:50:44 2022
$end
$version
	Icarus Verilog
$end
$timescale
	1ps
$end
$scope module mux2 $end
$var wire 4 ! d0 [3:0] $end
$upscope $end
$scope module mux2 $end
$var wire 4 " d1 [3:0] $end
$upscope $end
$scope module mux2 $end
$var wire 1 # s $end
$upscope $end
$scope module mux2 $end
$var wire 4 $ y [3:0] $end
$upscope $end
$enddefinitions $end
#0
$dumpvars
b0 $
0#
b0 "
b0 !
$end
#2000
1#
#4000
b0 $
0#
b1 "
#6000
b1 $
1#
#8000
b0 $
0#
b10 "
#10000
b10 $
1#
#12000
b0 $
0#
b11 "
#14000
b11 $
1#
#16000
b0 $
0#
b100 "
#18000
b100 $
1#
#20000
b0 $
0#
b101 "
#22000
b101 $
1#
#24000
b0 $
0#
b110 "
#26000
b110 $
1#
#28000
b0 $
0#
b111 "
#30000
b111 $
1#
#32000
b0 $
0#
b1000 "
#34000
b1000 $
1#
#36000
b0 $
0#
b1001 "
#38000
b1001 $
1#
#40000
b0 $
0#
b1010 "
#42000
b1010 $
1#
#44000
b0 $
0#
b1011 "
#46000
b1011 $
1#
#48000
b0 $
0#
b1100 "
#50000
b1100 $
1#
#52000
b0 $
0#
b1101 "
#54000
b1101 $
1#
#56000
b0 $
0#
b1110 "
#58000
b1110 $
1#
#60000
b0 $
0#
b1111 "
#62000
b1111 $
1#
#64000
b1 $
0#
b0 "
b1 !
#66000
b0 $
1#
#68000
b1 $
0#
b1 "
#70000
1#
#72000
b1 $
0#
b10 "
#74000
b10 $
1#
#76000
b1 $
0#
b11 "
#78000
b11 $
1#
#80000
b1 $
0#
b100 "
#82000
b100 $
1#
#84000
b1 $
0#
b101 "
#86000
b101 $
1#
#88000
b1 $
0#
b110 "
#90000
b110 $
1#
#92000
b1 $
0#
b111 "
#94000
b111 $
1#
#96000
b1 $
0#
b1000 "
#98000
b1000 $
1#
#100000
b1 $
0#
b1001 "
#102000
b1001 $
1#
#104000
b1 $
0#
b1010 "
#106000
b1010 $
1#
#108000
b1 $
0#
b1011 "
#110000
b1011 $
1#
#112000
b1 $
0#
b1100 "
#114000
b1100 $
1#
#116000
b1 $
0#
b1101 "
#118000
b1101 $
1#
#120000
b1 $
0#
b1110 "
#122000
b1110 $
1#
#124000
b1 $
0#
b1111 "
#126000
b1111 $
1#
#128000
b10 $
0#
b0 "
b10 !
#130000
b0 $
1#
#132000
b10 $
0#
b1 "
#134000
b1 $
1#
#136000
b10 $
0#
b10 "
#138000
1#
#140000
b10 $
0#
b11 "
#142000
b11 $
1#
#144000
b10 $
0#
b100 "
#146000
b100 $
1#
#148000
b10 $
0#
b101 "
#150000
b101 $
1#
#152000
b10 $
0#
b110 "
#154000
b110 $
1#
#156000
b10 $
0#
b111 "
#158000
b111 $
1#
#160000
b10 $
0#
b1000 "
#162000
b1000 $
1#
#164000
b10 $
0#
b1001 "
#166000
b1001 $
1#
#168000
b10 $
0#
b1010 "
#170000
b1010 $
1#
#172000
b10 $
0#
b1011 "
#174000
b1011 $
1#
#176000
b10 $
0#
b1100 "
#178000
b1100 $
1#
#180000
b10 $
0#
b1101 "
#182000
b1101 $
1#
#184000
b10 $
0#
b1110 "
#186000
b1110 $
1#
#188000
b10 $
0#
b1111 "
#190000
b1111 $
1#
#192000
b11 $
0#
b0 "
b11 !
#194000
b0 $
1#
#196000
b11 $
0#
b1 "
#198000
b1 $
1#
#200000
b11 $
0#
b10 "
#202000
b10 $
1#
#204000
b11 $
0#
b11 "
#206000
1#
#208000
b11 $
0#
b100 "
#210000
b100 $
1#
#212000
b11 $
0#
b101 "
#214000
b101 $
1#
#216000
b11 $
0#
b110 "
#218000
b110 $
1#
#220000
b11 $
0#
b111 "
#222000
b111 $
1#
#224000
b11 $
0#
b1000 "
#226000
b1000 $
1#
#228000
b11 $
0#
b1001 "
#230000
b1001 $
1#
#232000
b11 $
0#
b1010 "
#234000
b1010 $
1#
#236000
b11 $
0#
b1011 "
#238000
b1011 $
1#
#240000
b11 $
0#
b1100 "
#242000
b1100 $
1#
#244000
b11 $
0#
b1101 "
#246000
b1101 $
1#
#248000
b11 $
0#
b1110 "
#250000
b1110 $
1#
#252000
b11 $
0#
b1111 "
#254000
b1111 $
1#
#256000
b100 $
0#
b0 "
b100 !
#258000
b0 $
1#
#260000
b100 $
0#
b1 "
#262000
b1 $
1#
#264000
b100 $
0#
b10 "
#266000
b10 $
1#
#268000
b100 $
0#
b11 "
#270000
b11 $
1#
#272000
b100 $
0#
b100 "
#274000
1#
#276000
b100 $
0#
b101 "
#278000
b101 $
1#
#280000
b100 $
0#
b110 "
#282000
b110 $
1#
#284000
b100 $
0#
b111 "
#286000
b111 $
1#
#288000
b100 $
0#
b1000 "
#290000
b1000 $
1#
#292000
b100 $
0#
b1001 "
#294000
b1001 $
1#
#296000
b100 $
0#
b1010 "
#298000
b1010 $
1#
#300000
b100 $
0#
b1011 "
#302000
b1011 $
1#
#304000
b100 $
0#
b1100 "
#306000
b1100 $
1#
#308000
b100 $
0#
b1101 "
#310000
b1101 $
1#
#312000
b100 $
0#
b1110 "
#314000
b1110 $
1#
#316000
b100 $
0#
b1111 "
#318000
b1111 $
1#
#320000
b101 $
0#
b0 "
b101 !
#322000
b0 $
1#
#324000
b101 $
0#
b1 "
#326000
b1 $
1#
#328000
b101 $
0#
b10 "
#330000
b10 $
1#
#332000
b101 $
0#
b11 "
#334000
b11 $
1#
#336000
b101 $
0#
b100 "
#338000
b100 $
1#
#340000
b101 $
0#
b101 "
#342000
1#
#344000
b101 $
0#
b110 "
#346000
b110 $
1#
#348000
b101 $
0#
b111 "
#350000
b111 $
1#
#352000
b101 $
0#
b1000 "
#354000
b1000 $
1#
#356000
b101 $
0#
b1001 "
#358000
b1001 $
1#
#360000
b101 $
0#
b1010 "
#362000
b1010 $
1#
#364000
b101 $
0#
b1011 "
#366000
b1011 $
1#
#368000
b101 $
0#
b1100 "
#370000
b1100 $
1#
#372000
b101 $
0#
b1101 "
#374000
b1101 $
1#
#376000
b101 $
0#
b1110 "
#378000
b1110 $
1#
#380000
b101 $
0#
b1111 "
#382000
b1111 $
1#
#384000
b110 $
0#
b0 "
b110 !
#386000
b0 $
1#
#388000
b110 $
0#
b1 "
#390000
b1 $
1#
#392000
b110 $
0#
b10 "
#394000
b10 $
1#
#396000
b110 $
0#
b11 "
#398000
b11 $
1#
#400000
b110 $
0#
b100 "
#402000
b100 $
1#
#404000
b110 $
0#
b101 "
#406000
b101 $
1#
#408000
b110 $
0#
b110 "
#410000
1#
#412000
b110 $
0#
b111 "
#414000
b111 $
1#
#416000
b110 $
0#
b1000 "
#418000
b1000 $
1#
#420000
b110 $
0#
b1001 "
#422000
b1001 $
1#
#424000
b110 $
0#
b1010 "
#426000
b1010 $
1#
#428000
b110 $
0#
b1011 "
#430000
b1011 $
1#
#432000
b110 $
0#
b1100 "
#434000
b1100 $
1#
#436000
b110 $
0#
b1101 "
#438000
b1101 $
1#
#440000
b110 $
0#
b1110 "
#442000
b1110 $
1#
#444000
b110 $
0#
b1111 "
#446000
b1111 $
1#
#448000
b111 $
0#
b0 "
b111 !
#450000
b0 $
1#
#452000
b111 $
0#
b1 "
#454000
b1 $
1#
#456000
b111 $
0#
b10 "
#458000
b10 $
1#
#460000
b111 $
0#
b11 "
#462000
b11 $
1#
#464000
b111 $
0#
b100 "
#466000
b100 $
1#
#468000
b111 $
0#
b101 "
#470000
b101 $
1#
#472000
b111 $
0#
b110 "
#474000
b110 $
1#
#476000
b111 $
0#
b111 "
#478000
1#
#480000
b111 $
0#
b1000 "
#482000
b1000 $
1#
#484000
b111 $
0#
b1001 "
#486000
b1001 $
1#
#488000
b111 $
0#
b1010 "
#490000
b1010 $
1#
#492000
b111 $
0#
b1011 "
#494000
b1011 $
1#
#496000
b111 $
0#
b1100 "
#498000
b1100 $
1#
#500000
b111 $
0#
b1101 "
#502000
b1101 $
1#
#504000
b111 $
0#
b1110 "
#506000
b1110 $
1#
#508000
b111 $
0#
b1111 "
#510000
b1111 $
1#
#512000
b1000 $
0#
b0 "
b1000 !
#514000
b0 $
1#
#516000
b1000 $
0#
b1 "
#518000
b1 $
1#
#520000
b1000 $
0#
b10 "
#522000
b10 $
1#
#524000
b1000 $
0#
b11 "
#526000
b11 $
1#
#528000
b1000 $
0#
b100 "
#530000
b100 $
1#
#532000
b1000 $
0#
b101 "
#534000
b101 $
1#
#536000
b1000 $
0#
b110 "
#538000
b110 $
1#
#540000
b1000 $
0#
b111 "
#542000
b111 $
1#
#544000
b1000 $
0#
b1000 "
#546000
1#
#548000
b1000 $
0#
b1001 "
#550000
b1001 $
1#
#552000
b1000 $
0#
b1010 "
#554000
b1010 $
1#
#556000
b1000 $
0#
b1011 "
#558000
b1011 $
1#
#560000
b1000 $
0#
b1100 "
#562000
b1100 $
1#
#564000
b1000 $
0#
b1101 "
#566000
b1101 $
1#
#568000
b1000 $
0#
b1110 "
#570000
b1110 $
1#
#572000
b1000 $
0#
b1111 "
#574000
b1111 $
1#
#576000
b1001 $
0#
b0 "
b1001 !
#578000
b0 $
1#
#580000
b1001 $
0#
b1 "
#582000
b1 $
1#
#584000
b1001 $
0#
b10 "
#586000
b10 $
1#
#588000
b1001 $
0#
b11 "
#590000
b11 $
1#
#592000
b1001 $
0#
b100 "
#594000
b100 $
1#
#596000
b1001 $
0#
b101 "
#598000
b101 $
1#
#600000
b1001 $
0#
b110 "
#602000
b110 $
1#
#604000
b1001 $
0#
b111 "
#606000
b111 $
1#
#608000
b1001 $
0#
b1000 "
#610000
b1000 $
1#
#612000
b1001 $
0#
b1001 "
#614000
1#
#616000
b1001 $
0#
b1010 "
#618000
b1010 $
1#
#620000
b1001 $
0#
b1011 "
#622000
b1011 $
1#
#624000
b1001 $
0#
b1100 "
#626000
b1100 $
1#
#628000
b1001 $
0#
b1101 "
#630000
b1101 $
1#
#632000
b1001 $
0#
b1110 "
#634000
b1110 $
1#
#636000
b1001 $
0#
b1111 "
#638000
b1111 $
1#
#640000
b1010 $
0#
b0 "
b1010 !
#642000
b0 $
1#
#644000
b1010 $
0#
b1 "
#646000
b1 $
1#
#648000
b1010 $
0#
b10 "
#650000
b10 $
1#
#652000
b1010 $
0#
b11 "
#654000
b11 $
1#
#656000
b1010 $
0#
b100 "
#658000
b100 $
1#
#660000
b1010 $
0#
b101 "
#662000
b101 $
1#
#664000
b1010 $
0#
b110 "
#666000
b110 $
1#
#668000
b1010 $
0#
b111 "
#670000
b111 $
1#
#672000
b1010 $
0#
b1000 "
#674000
b1000 $
1#
#676000
b1010 $
0#
b1001 "
#678000
b1001 $
1#
#680000
b1010 $
0#
b1010 "
#682000
1#
#684000
b1010 $
0#
b1011 "
#686000
b1011 $
1#
#688000
b1010 $
0#
b1100 "
#690000
b1100 $
1#
#692000
b1010 $
0#
b1101 "
#694000
b1101 $
1#
#696000
b1010 $
0#
b1110 "
#698000
b1110 $
1#
#700000
b1010 $
0#
b1111 "
#702000
b1111 $
1#
#704000
b1011 $
0#
b0 "
b1011 !
#706000
b0 $
1#
#708000
b1011 $
0#
b1 "
#710000
b1 $
1#
#712000
b1011 $
0#
b10 "
#714000
b10 $
1#
#716000
b1011 $
0#
b11 "
#718000
b11 $
1#
#720000
b1011 $
0#
b100 "
#722000
b100 $
1#
#724000
b1011 $
0#
b101 "
#726000
b101 $
1#
#728000
b1011 $
0#
b110 "
#730000
b110 $
1#
#732000
b1011 $
0#
b111 "
#734000
b111 $
1#
#736000
b1011 $
0#
b1000 "
#738000
b1000 $
1#
#740000
b1011 $
0#
b1001 "
#742000
b1001 $
1#
#744000
b1011 $
0#
b1010 "
#746000
b1010 $
1#
#748000
b1011 $
0#
b1011 "
#750000
1#
#752000
b1011 $
0#
b1100 "
#754000
b1100 $
1#
#756000
b1011 $
0#
b1101 "
#758000
b1101 $
1#
#760000
b1011 $
0#
b1110 "
#762000
b1110 $
1#
#764000
b1011 $
0#
b1111 "
#766000
b1111 $
1#
#768000
b1100 $
0#
b0 "
b1100 !
#770000
b0 $
1#
#772000
b1100 $
0#
b1 "
#774000
b1 $
1#
#776000
b1100 $
0#
b10 "
#778000
b10 $
1#
#780000
b1100 $
0#
b11 "
#782000
b11 $
1#
#784000
b1100 $
0#
b100 "
#786000
b100 $
1#
#788000
b1100 $
0#
b101 "
#790000
b101 $
1#
#792000
b1100 $
0#
b110 "
#794000
b110 $
1#
#796000
b1100 $
0#
b111 "
#798000
b111 $
1#
#800000
b1100 $
0#
b1000 "
#802000
b1000 $
1#
#804000
b1100 $
0#
b1001 "
#806000
b1001 $
1#
#808000
b1100 $
0#
b1010 "
#810000
b1010 $
1#
#812000
b1100 $
0#
b1011 "
#814000
b1011 $
1#
#816000
b1100 $
0#
b1100 "
#818000
1#
#820000
b1100 $
0#
b1101 "
#822000
b1101 $
1#
#824000
b1100 $
0#
b1110 "
#826000
b1110 $
1#
#828000
b1100 $
0#
b1111 "
#830000
b1111 $
1#
#832000
b1101 $
0#
b0 "
b1101 !
#834000
b0 $
1#
#836000
b1101 $
0#
b1 "
#838000
b1 $
1#
#840000
b1101 $
0#
b10 "
#842000
b10 $
1#
#844000
b1101 $
0#
b11 "
#846000
b11 $
1#
#848000
b1101 $
0#
b100 "
#850000
b100 $
1#
#852000
b1101 $
0#
b101 "
#854000
b101 $
1#
#856000
b1101 $
0#
b110 "
#858000
b110 $
1#
#860000
b1101 $
0#
b111 "
#862000
b111 $
1#
#864000
b1101 $
0#
b1000 "
#866000
b1000 $
1#
#868000
b1101 $
0#
b1001 "
#870000
b1001 $
1#
#872000
b1101 $
0#
b1010 "
#874000
b1010 $
1#
#876000
b1101 $
0#
b1011 "
#878000
b1011 $
1#
#880000
b1101 $
0#
b1100 "
#882000
b1100 $
1#
#884000
b1101 $
0#
b1101 "
#886000
1#
#888000
b1101 $
0#
b1110 "
#890000
b1110 $
1#
#892000
b1101 $
0#
b1111 "
#894000
b1111 $
1#
#896000
b1110 $
0#
b0 "
b1110 !
#898000
b0 $
1#
#900000
b1110 $
0#
b1 "
#902000
b1 $
1#
#904000
b1110 $
0#
b10 "
#906000
b10 $
1#
#908000
b1110 $
0#
b11 "
#910000
b11 $
1#
#912000
b1110 $
0#
b100 "
#914000
b100 $
1#
#916000
b1110 $
0#
b101 "
#918000
b101 $
1#
#920000
b1110 $
0#
b110 "
#922000
b110 $
1#
#924000
b1110 $
0#
b111 "
#926000
b111 $
1#
#928000
b1110 $
0#
b1000 "
#930000
b1000 $
1#
#932000
b1110 $
0#
b1001 "
#934000
b1001 $
1#
#936000
b1110 $
0#
b1010 "
#938000
b1010 $
1#
#940000
b1110 $
0#
b1011 "
#942000
b1011 $
1#
#944000
b1110 $
0#
b1100 "
#946000
b1100 $
1#
#948000
b1110 $
0#
b1101 "
#950000
b1101 $
1#
#952000
b1110 $
0#
b1110 "
#954000
1#
#956000
b1110 $
0#
b1111 "
#958000
b1111 $
1#
#960000
b1111 $
0#
b0 "
b1111 !
#962000
b0 $
1#
#964000
b1111 $
0#
b1 "
#966000
b1 $
1#
#968000
b1111 $
0#
b10 "
#970000
b10 $
1#
#972000
b1111 $
0#
b11 "
#974000
b11 $
1#
#976000
b1111 $
0#
b100 "
#978000
b100 $
1#
#980000
b1111 $
0#
b101 "
#982000
b101 $
1#
#984000
b1111 $
0#
b110 "
#986000
b110 $
1#
#988000
b1111 $
0#
b111 "
#990000
b111 $
1#
#992000
b1111 $
0#
b1000 "
#994000
b1000 $
1#
#996000
b1111 $
0#
b1001 "
#998000
b1001 $
1#
#1000000
b1111 $
0#
b1010 "
#1002000
b1010 $
1#
#1004000
b1111 $
0#
b1011 "
#1006000
b1011 $
1#
#1008000
b1111 $
0#
b1100 "
#1010000
b1100 $
1#
#1012000
b1111 $
0#
b1101 "
#1014000
b1101 $
1#
#1016000
b1111 $
0#
b1110 "
#1018000
b1110 $
1#
#1020000
b1111 $
0#
b1111 "
#1022000
1#
