hdl/4_20_synchronizer/hdl/vhdl/sync.vhd
library IEEE; use IEEE.STD_LOGIC_1164.all;

entity sync is
	port (
		clk:    in   STD_LOGIC;
    d:      in   STD_LOGIC;
    q:      out  STD_LOGIC
	);
end;

architecture good of sync is
  signal n1: STD_LOGIC;
begin

  process (clk) begin
    if rising_edge(clk) then
      n1 <= d;
      q <= n1;
    end if;
  end process;

end;

hdl/4_20_synchronizer/tests/wave_sv.vcd
$date
	Thu Sep 29 14:51:11 2022
$end
$version
	Icarus Verilog
$end
$timescale
	1ps
$end
$scope module sync $end
$var wire 1 ! clk $end
$upscope $end
$scope module sync $end
$var reg 1 " n1 $end
$upscope $end
$scope module sync $end
$var wire 1 # d $end
$upscope $end
$scope module sync $end
$var reg 1 $ q $end
$upscope $end
$enddefinitions $end
#0
$dumpvars
x$
1#
1"
1!
$end
#5000000
0!
#10000000
1$
1!
#15000000
0#
0!
#20000000
0"
1!
#25000000
1#
0!
#30000000
0$
1"
1!
#35000000
0#
0!
#40000000
1$
0"
1!
#45000000
1#
0!
#50000000
0$
1"
1!
#55000000
0#
0!
#60000000
1$
0"
1!
#65000000
1#
0!
#70000000
0$
1"
1!
#75000000
0#
0!
#80000000
1$
0"
1!
#85000000
1#
0!
#90000000
0$
1"
1!
#95000000
0#
0!
#100000000
1$
0"
1!
#105000000
1#
0!
#110000000
0$
1"
1!
