hdl/4_22_inv/hdl/sv/inv.sv
module inv (

  input   logic [3:0] a,  // represents a 4-bit bus (little-endian order,
                          // where the least significant bit has the smallest 
                          // bit number

  output  logic [3:0] y   // represents a 4-bit bus (little endian order)

);

  // always_comb reevaluates any time and right hand side signals change
  // in either <= (nonblocking) or = (blocking) assignments
  //
  // Remember, blocking assignments are executed in the order they appear;
  // nonblocking assignments are evaluated concurrently / all statements are
  // evaluated before any of the left hand sides are updated.
  always_comb
    y = ~a;

`ifdef  COCOTB_SIM 
initial
 begin
    $dumpfile("wave_sv.vcd");
    $dumpvars(
      0,
      a,
      y
    );
    #5;
 end
 `endif

endmodule

hdl/4_22_inv/tests/wave_sv.vcd
$date
	Tue Sep 20 14:47:38 2022
$end
$version
	Icarus Verilog
$end
$timescale
	1ps
$end
$scope module inv $end
$var wire 4 ! a [3:0] $end
$upscope $end
$scope module inv $end
$var reg 4 " y [3:0] $end
$upscope $end
$enddefinitions $end
#0
$dumpvars
b1111 "
b0 !
$end
#1000
b1110 "
b1 !
#2000
b1101 "
b10 !
#3000
b1100 "
b11 !
#4000
b1011 "
b100 !
#5000
b1010 "
b101 !
#6000
b1001 "
b110 !
#7000
b1000 "
b111 !
#8000
b111 "
b1000 !
#9000
b110 "
b1001 !
#10000
b101 "
b1010 !
#11000
b100 "
b1011 !
#12000
b11 "
b1100 !
#13000
b10 "
b1101 !
#14000
b1 "
b1110 !
#15000
b0 "
b1111 !
