hdl/4_30_divby3/hdl/vhdl/divby3.vhd
library IEEE; use IEEE.STD_LOGIC_1164.all;

entity divby3 is
	port (
		clk, reset:     in  STD_LOGIC;
		y:              out STD_LOGIC
	);
end;

architecture synth of divby3 is
  type statetype is (S0, S1, S2);
  signal state, nextstate: statetype;
begin

  -- state register
  process (clk, reset) begin
    if reset then state <= S0;
    elsif rising_edge(clk) then
      state <= nextstate;
    end if;
  end process;

  -- next state logic
  nextstate <= S1 when state = S0 else
               S2 when state = S1 else
               S0;

  -- output logic
  y <= '1' when state = S0 else '0';


end;

hdl/4_30_divby3/tests/wave_vhdl.vcd
$date
  Tue Sep 20 14:48:05 2022
$end
$version
  GHDL v0
$end
$timescale
  1 fs
$end
$scope module standard $end
$upscope $end
$scope module textio $end
$upscope $end
$scope module std_logic_1164 $end
$upscope $end
$scope module divby3 $end
$var reg 1 ! clk $end
$var reg 1 " reset $end
$var reg 1 # y $end
$comment state is not handled $end
$comment nextstate is not handled $end
$upscope $end
$enddefinitions $end
#0
1!
U"
1#
#5000000000
0!
1"
#10000000000
1!
#15000000000
0!
0"
#20000000000
1!
0#
#25000000000
0!
#30000000000
1!
#35000000000
0!
#40000000000
1!
1#
#45000000000
0!
#50000000000
1!
0#
#55000000000
0!
#60000000000
1!
#65000000000
0!
#70000000000
1!
1#
#75000000000
0!
#80000000000
1!
0#
#85000000000
0!
#90000000000
1!
#95000000000
0!
#100000000000
1!
1#
#105000000000
0!
#110000000000
1!
0#
#115000000000
0!
#120000000000
1!
#125000000000
0!
#130000000000
1!
1#
#135000000000
0!
#140000000000
1!
0#
#145000000000
0!
#150000000000
1!
#155000000000
0!
#160000000000
1!
1#
#165000000000
0!
#170000000000
1!
0#
#175000000000
0!
#180000000000
1!
#185000000000
0!
#190000000000
1!
1#
#195000000000
0!
#200000000000
1!
0#
#205000000000
0!
#210000000000
1!
#215000000000
0!
#220000000000
1!
1#
#225000000000
0!
#230000000000
1!
0#
#235000000000
0!
#240000000000
1!
#245000000000
0!
#250000000000
1!
1#
#255000000000
0!
#260000000000
1!
0#
#265000000000
0!
#270000000000
1!
#275000000000
0!
#280000000000
1!
1#
#285000000000
0!
#290000000000
1!
0#
#295000000000
0!
#300000000000
1!
#305000000000
0!
#310000000000
1!
1#
#315000000000
0!
#320000000000
1!
0#
