hdl/4_01_sillyfunction/hdl/sv/sillyfunction.sv
module sillyfunction(
	input   logic a, b, c,
	output  logic y
);

  // this is a continuous assignment statement, ends with a semicolon,
  // and output changes in direct response to inputs
  assign y = ~a & ~b & ~c |
    a & ~b & ~c |
    a & ~b & c;

endmodule

hdl/4_01_sillyfunction/tests/wave_vhdl.vcd
$date
  Sun Sep 25 22:04:41 2022
$end
$version
  GHDL v0
$end
$timescale
  1 fs
$end
$scope module standard $end
$upscope $end
$scope module textio $end
$upscope $end
$scope module std_logic_1164 $end
$upscope $end
$scope module sillyfunction $end
$var reg 1 ! a $end
$var reg 1 " b $end
$var reg 1 # c $end
$var reg 1 $ y $end
$upscope $end
$enddefinitions $end
#0
0!
0"
0#
1$
#1000000
1#
0$
#2000000
1"
0#
#3000000
1#
#4000000
1!
0"
0#
1$
#5000000
1#
#6000000
1"
0#
0$
#7000000
1#
