hdl/4_27_priority_dontcare/hdl/sv/priority.sv
module priorityckt (
	input   logic [3:0] a,
  output  logic [3:0] y
);

// in SystemVerilog, if statements must always appear within always statements.
always_comb
  casez(a)
    4'b1???: y = 4'b1000;
    4'b01??: y = 4'b0100;
    4'b001?: y = 4'b0010;
    4'b0001: y = 4'b0001;
    default: y = 4'b0000;
  endcase

`ifdef  COCOTB_SIM 
initial
 begin
    $dumpfile("wave_sv.vcd");
    $dumpvars(
      0,
      a,
      y
    );
    #5;
 end
`endif

endmodule

hdl/4_27_priority_dontcare/tests/wave_vhdl.vcd
$date
  Sun Sep 25 22:06:35 2022
$end
$version
  GHDL v0
$end
$timescale
  1 fs
$end
$scope module standard $end
$upscope $end
$scope module textio $end
$upscope $end
$scope module std_logic_1164 $end
$upscope $end
$scope module priorityckt $end
$var reg 4 ! a[3:0] $end
$var reg 4 " y[3:0] $end
$upscope $end
$enddefinitions $end
#0
b0000 !
b0000 "
#1000000
b0001 !
b0001 "
#2000000
b0010 !
b0010 "
#3000000
b0011 !
#4000000
b0100 !
b0100 "
#5000000
b0101 !
#6000000
b0110 !
#7000000
b0111 !
#8000000
b1000 !
b1000 "
#9000000
b1001 !
#10000000
b1010 !
#11000000
b1011 !
#12000000
b1100 !
#13000000
b1101 !
#14000000
b1110 !
#15000000
b1111 !
