hdl/4_13_delays/hdl/vhdl/example.vhd
library IEEE; use IEEE.STD_LOGIC_1164.all;

entity example is
	port (
    a, b, c:  in  STD_LOGIC;
    y:        out STD_LOGIC
	);
end;

architecture synth of example is
  -- note that here we define some intermediate signals
  signal ab, bb, cb, n1, n2, n3: STD_LOGIC;
begin

  -- note that in VHDL the after clause is used to denote delay
  -- the units specified here are nanoseconds
  ab <= not a after 1 ns;
  bb <= not b after 1 ns;
  cb <= not c after 1 ns;
  n1 <= ab and bb and cb after 2 ns;
  n2 <= a and bb and cb after 2 ns;
  n3 <= a and bb and c after 2 ns;
  y <= (n1 or n2 or n3) after 4 ns;

end;

hdl/4_13_delays/tests/wave_sv.vcd
$date
	Mon Sep 19 21:39:09 2022
$end
$version
	Icarus Verilog
$end
$timescale
	1ps
$end
$scope module example $end
$var wire 1 ! a $end
$upscope $end
$scope module example $end
$var wire 1 " b $end
$upscope $end
$scope module example $end
$var wire 1 # c $end
$upscope $end
$scope module example $end
$var wire 1 $ ab $end
$upscope $end
$scope module example $end
$var wire 1 % bb $end
$upscope $end
$scope module example $end
$var wire 1 & cb $end
$upscope $end
$scope module example $end
$var wire 1 ' n1 $end
$upscope $end
$scope module example $end
$var wire 1 ( n2 $end
$upscope $end
$scope module example $end
$var wire 1 ) n3 $end
$upscope $end
$scope module example $end
$var wire 1 * y $end
$upscope $end
$enddefinitions $end
#0
$dumpvars
x*
x)
x(
x'
x&
x%
x$
0#
0"
0!
$end
#1000
1$
1%
1&
#2000
0(
0)
#3000
1'
#7000
1*
#10000
1#
#11000
0&
#13000
0'
#17000
0*
#20000
1"
0#
#21000
0%
1&
#30000
1#
#31000
0&
#40000
1!
0"
0#
#41000
0$
1%
1&
#43000
1(
#47000
1*
#50000
1#
#51000
0&
#52000
1)
#53000
0(
#60000
1"
0#
#61000
0%
1&
#62000
0)
#66000
0*
#70000
1#
#71000
0&
