hdl/mode/hdl/vhdl/mode.vhd
library IEEE; use IEEE.STD_LOGIC_1164.all;

entity mode is
	port (
		clk, reset:     in  STD_LOGIC;
    p:              in  STD_LOGIC;
    r:              in  STD_LOGIC;
    m:              out STD_LOGIC
	);
end;

architecture synth of mode is
  type statetype is (S0, S1);
  signal state, nextstate: statetype;
begin

  -- state register
  process (clk, reset) begin
    if reset then
      state <= S0;
    elsif rising_edge(clk) then
      state <= nextstate;
    end if;
  end process;

  -- next state logic
  process (all) begin
    case state is
      when S0 =>
        if p then
          nextstate <= S1;
        else 
          nextstate <= S0;
        end if;
      when S1 =>
        if r then
          nextstate <= S0;
        else
          nextstate <= S1;
        end if;
      when others =>
        nextstate <= S0;
    end case;
  end process;

  -- output logic
  m <= '1' when state = S1 else '0';


end;

hdl/mode/tests/wave_sv.vcd
$date
	Tue Oct 18 04:43:15 2022
$end
$version
	Icarus Verilog
$end
$timescale
	1ps
$end
$scope module mode $end
$var wire 1 ! clk $end
$upscope $end
$scope module mode $end
$var wire 1 " reset $end
$upscope $end
$scope module mode $end
$var wire 1 # p $end
$upscope $end
$scope module mode $end
$var wire 1 $ r $end
$upscope $end
$scope module mode $end
$var wire 1 % m $end
$upscope $end
$scope module mode $end
$var reg 1 & state $end
$upscope $end
$scope module mode $end
$var reg 1 ' nextstate $end
$upscope $end
$enddefinitions $end
#0
$dumpvars
0'
0&
0%
z$
z#
z"
1!
$end
#5000000
0$
0#
1"
0!
#10000000
1!
#15000000
1$
0"
0!
#20000000
1!
#25000000
0$
0!
#30000000
1!
#35000000
0!
#40000000
1!
#45000000
1$
0!
#50000000
1!
#55000000
1'
1#
0!
#60000000
0'
1%
1&
1!
#65000000
1'
0$
0!
#70000000
1!
#75000000
0!
#80000000
1!
#85000000
0'
1$
0!
#90000000
1'
0%
0&
1!
#95000000
0!
#100000000
0'
1%
1&
1!
#105000000
1'
0$
0!
#110000000
1!
#115000000
0!
#120000000
1!
#125000000
0'
1$
0!
#130000000
1'
0%
0&
1!
#135000000
0'
0#
0!
#140000000
1!
#145000000
0$
0!
#150000000
1!
#155000000
0!
#160000000
1!
#165000000
1$
0!
